{"cameraMode":{"drawMode":0,"name":"Shaded","section":"Shading Mode"},"sceneLighting":true,"audioPlay":false,"sceneViewState":{"m_AlwaysRefresh":false,"showFog":true,"showSkybox":false,"showFlares":true,"showImageEffects":true,"showParticleSystems":true,"showVisualEffectGraphs":true,"m_FxEnabled":true},"in2DMode":false,"pivot":{"x":0.0,"y":1.0,"z":0.0},"rotation":{"x":0.16052967309951783,"y":-0.7849489450454712,"z":0.2276766449213028,"w":0.553425669670105},"size":2.4248712062835695,"orthographic":false}